CHANGES.txt
LICENSE.txt
README.txt
setup.py
YamlVariablesLibrary/__init__.py
YamlVariablesLibrary/_keywords.py
YamlVariablesLibrary/version.py
YamlVariablesLibrary/tests/__init__.py
YamlVariablesLibrary/tests/env.py
YamlVariablesLibrary/tests/run_tests.py
robotframework_YamlVariablesLibrary.egg-info/PKG-INFO
robotframework_YamlVariablesLibrary.egg-info/SOURCES.txt
robotframework_YamlVariablesLibrary.egg-info/dependency_links.txt
robotframework_YamlVariablesLibrary.egg-info/requires.txt
robotframework_YamlVariablesLibrary.egg-info/top_level.txt