Metadata-Version: 1.0
Name: robotframework-YamlVariablesLibrary
Version: 0.0.5-dev
Summary: Robot Framework Library allowing to variables stored in yaml files
Home-page: https://code.google.com/p/robotframework-YamlVariablesLibrary/
Author: Jules Barnes
Author-email: jules@julesbarnes.com
License: LICENSE.txt
Platform: UNKNOWN
